pcfv/__init__.py
pcfv/dataset.py
pcfv/metric.py
pcfv/noise.py
pcfv/train.py
pcfv/utils.py
pcfv/layers/ConvBlock.py
pcfv/layers/MSDConvBlock.py
pcfv/layers/ScalingBlock.py
pcfv/layers/__init__.py
pcfv/networks/MSDNet.py
pcfv/networks/UNet.py
pcfv/networks/__init__.py
pcfv-0.0.19.dist-info/LICENSE
pcfv-0.0.19.dist-info/METADATA
pcfv-0.0.19.dist-info/WHEEL
pcfv-0.0.19.dist-info/top_level.txt
pcfv-0.0.19.dist-info/RECORD
