Metadata-Version: 2.1
Name: pcfv
Version: 0.0.19
Summary: The common used function with pytorch for vision tasks
Home-page: https://github.com/jiayangshi/pcf
Author: Jiayang Shi
Author-email: j.shi@liacs.leidenuniv.nl
License: MIT
Platform: UNKNOWN
Classifier: Development Status :: 1 - Planning
Classifier: License :: OSI Approved :: MIT License
Classifier: Programming Language :: Python :: 3
Classifier: Topic :: Scientific/Engineering :: Artificial Intelligence
Requires-Python: >=3.7
License-File: LICENSE
Requires-Dist: torch
Requires-Dist: numpy
Requires-Dist: matplotlib
Requires-Dist: Pillow
